setup.cfg
setup.py
programo/__init__.py
programo/class1.py
programo/utils.py
programo.egg-info/PKG-INFO
programo.egg-info/SOURCES.txt
programo.egg-info/dependency_links.txt
programo.egg-info/not-zip-safe
programo.egg-info/requires.txt
programo.egg-info/top_level.txt