Metadata-Version: 1.1
Name: programo
Version: 0.1.0
Summary: Probabilistic Graphical Models in Python
Home-page: https://github.com/tsitsimis/programo
Author: Theodore Tsitsimis
Author-email: th.tsitsimis@gmail.com
License: MIT
Download-URL: https://github.com/tsitsimis/programo/archive/0.0.1.tar.gz
Keywords: graphical models,machine learning
Platform: UNKNOWN
Classifier: Development Status :: 3 - Alpha
Classifier: Intended Audience :: Developers
Classifier: Topic :: Software Development :: Build Tools
Classifier: License :: OSI Approved :: MIT License
Classifier: Programming Language :: Python :: 3.4
